{"ner_tags":["B-Reference","O","O","O","B-Predicate","O","B-Concept","O","O","O","O","B-Concept","O","O","B-Action","B-Concept","O","O","O","B-Concept","O","O","B-Concept","O","O","O"],"tokens":["los","que","se","encuentran","dentro","del","cuerpo","pueden","quiz\u00e1","no","ser","obvios","y","pueden","lesionar","\u00f3rganos",",","incluso","el","cerebro",",","los","pulmones","y","otros","."]}
{"ner_tags":["O","O","O","O","O","O","B-Action","O","B-Concept","O","B-Action","B-Concept","O","O","B-Concept","O","O","O","O","O","B-Action","O","B-Concept","B-Concept","O","O","B-Predicate","O","O","B-Concept","O"],"tokens":["si","alguna","vez","se","le","ha","incrustado","una","astilla","o","tuvo","arena","en","el","ojo",",","usted","sabe","qu\u00e9","es","tener","un","objeto","extra\u00f1o","en","alguna","parte","de","su","cuerpo","."]}
{"ner_tags":["O","B-Concept","I-Concept","O","B-Concept","O","O","O","B-Concept","O","B-Action","O","B-Concept","O"],"tokens":["la","tomograf\u00eda","computarizada","(","tc",")","es","una","tecnolog\u00eda","para","diagn\u00f3stico","con","im\u00e1genes","."]}
{"ner_tags":["O","B-Concept","O","O","B-Concept","O","B-Concept","O","O","B-Concept","I-Concept","O"],"tokens":["el","tratamiento","puede","incluir","antibi\u00f3ticos",",","analg\u00e9sicos","y","una","dieta","l\u00edquida","."]}
{"ner_tags":["O","O","B-Concept","B-Predicate","B-Concept","O","O","B-Concept","B-Concept","O","B-Action","O","B-Action","O","B-Action","B-Concept","B-Concept","O","B-Action","O","B-Concept","O"],"tokens":["en","los","casos","m\u00e1s","severos",",","los","adolescentes","intimidados","pueden","sentir","la","necesidad","de","tomar","medidas","dr\u00e1sticas","o","reaccionar","con","violencia","."]}
{"ner_tags":["O","O","O","O","B-Concept","I-Concept","O","O","B-Concept","B-Predicate","I-Predicate","O","O","B-Concept","I-Concept","O"],"tokens":["sin","embargo",",","la","enfermedad","cardiaca","es","la","asesina","n\u00famero","uno","en","los","estados","unidos","."]}
{"ner_tags":["O","B-Concept","B-Concept","O","B-Concept","I-Concept","O","O","B-Concept","O"],"tokens":["los","tumores","malignos","de","gl\u00e1ndulas","suprarrenales","son","poco","comunes","."]}
{"ner_tags":["O","B-Action","O","O","B-Concept","I-Concept","B-Action","O","O","B-Concept","I-Concept","I-Concept","I-Concept","O"],"tokens":["la","recuperaci\u00f3n","de","un","ataque","cerebral","involucra","a","varios","profesionales","de","la","salud","."]}
{"ner_tags":["O","O","B-Action","O","O","O","B-Predicate","O","B-Concept","O","B-Concept","O","O","B-Predicate","B-Concept","O","O","B-Concept","O"],"tokens":["algunas","veces","se","puede","sentir","el","sabor","del","l\u00edquido","del","est\u00f3mago","en","la","parte","posterior","de","la","boca","."]}
{"ner_tags":["B-Predicate","O","O","B-Concept","O","O","B-Predicate","O","B-Concept","B-Concept","O","B-Action","B-Concept","O","O","B-Concept","O"],"tokens":["luego","de","la","cirug\u00eda",",","la","mayor\u00eda","de","pacientes","trasplantados","pueden","volver","a","sus","actividades","normales","."]}
{"ner_tags":["O","B-Predicate","O","O","B-Concept","O","B-Reference","B-Action","O","B-Action","O","B-Concept","O","O","B-Action","B-Concept","O","B-Concept","O"],"tokens":["la","mayor\u00eda","de","las","personas","que","lo","padece","ha","trabajado","en","lugares","donde","quiz\u00e1s","inhalaron","part\u00edculas","de","asbesto","."]}
{"ner_tags":["O","B-Concept","O","B-Concept","B-Action","O","B-Concept","O","O","B-Action","O","O","O","B-Concept","B-Concept","O","O","O","B-Predicate","O","B-Concept","B-Concept","O"],"tokens":["un","testamento","en","vida","indica","qu\u00e9","tratamientos","usted","quisiera","recibir","si","tuviera","una","enfermedad","mortal","y","estuviera","en","estado","de","inconsciencia","permanente","."]}
{"ner_tags":["O","B-Action","O","O","B-Concept","I-Concept","O","B-Concept","I-Concept","I-Concept","O","O","B-Concept","O"],"tokens":["la","falta","de","las","vitaminas","b12","o","vitaminas","b","6","puede","causar","anemia","."]}
{"ner_tags":["O","B-Reference","O","O","O","B-Action","O","B-Predicate","O","O","B-Concept","O","O","O","B-Concept","O","O","B-Concept","O","B-Concept","O","O","B-Concept","O"],"tokens":["en","este","caso",",","se","coloca","una","gota","de","una","medicina","que","se","llama","atropina","en","el","ojo","``","bueno","''","del","ni\u00f1o","."]}
{"ner_tags":["O","O","B-Predicate","B-Concept","O","B-Reference","B-Action","O","B-Reference","O","B-Predicate","O","O","B-Concept","B-Action","B-Concept","O"],"tokens":["tambi\u00e9n","es","m\u00e1s","probable","que","lo","sufra","si","usted","o","miembros","de","su","familia","tienen","depresi\u00f3n","."]}
{"ner_tags":["O","B-Concept","O","O","O","O","O","O","O","O","O","O","B-Concept","O","B-Concept","B-Concept","O","B-Action","O","O","B-Concept","O","B-Predicate","B-Concept","O"],"tokens":["las","convulsiones","pueden","tener","muchas","causas",",","entre","las","que","se","incluyen","medicinas",",","fiebre","alta",",","lesiones","en","la","cabeza","y","ciertas","enfermedades","."]}
{"ner_tags":["O","B-Concept","O","O","O","O","O","B-Action","O","B-Concept","O"],"tokens":["la","conjuntivitis",",","en","general",",","no","afecta","la","vista","."]}
{"ner_tags":["B-Predicate","B-Concept","I-Concept","I-Concept","O","O","B-Concept","O","B-Action","B-Concept","O","B-Concept","O","B-Predicate","B-Concept","O","B-Concept","O","O","O","O","B-Concept","I-Concept","I-Concept","O"],"tokens":["algunos","asilos","de","ancianos","cuentan","con","unidades","de","cuidados","especiales","para","personas","con","problemas","serios","de","memoria",",","tales","como","la","enfermedad","de","alzheimer","."]}
{"ner_tags":["B-Action","O","B-Action","O","B-Action","O","B-Predicate","O","O","B-Reference","B-Action","O"],"tokens":["dejar","de","fumar","puede","reducir","el","riesgo","de","presentar","estos","problemas","."]}
{"ner_tags":["O","B-Concept","O","B-Action","O","O","B-Concept","O","B-Predicate","B-Predicate","O","B-Concept","O","O","O","B-Concept","I-Concept","O","B-Concept","O","O","O","B-Action","O","O","B-Concept","O"],"tokens":["el","alcohol","puede","da\u00f1ar","a","su","beb\u00e9","en","cualquier","etapa","del","embarazo",",","inclusive","los","primeros","meses","cuando","usted","quiz\u00e1s","todav\u00eda","no","sepa","que","esta","embarazada","."]}
{"ner_tags":["O","B-Concept","I-Concept","O","B-Action","O","O","B-Concept","O","O","B-Action","O","O","O","B-Action","O","B-Action","O"],"tokens":["la","insuficiencia","cardiaca","no","significa","que","el","coraz\u00f3n","se","ha","detenido","o","est\u00e1","por","dejar","de","funcionar","."]}
{"ner_tags":["O","B-Concept","O","B-Concept","O","O","O","O","B-Concept","O","B-Concept","I-Concept","O"],"tokens":["la","vaginitis","es","com\u00fan",",","especialmente","en","las","mujeres","en","edad","reproductiva","."]}
{"ner_tags":["O","B-Concept","B-Action","B-Concept","O","B-Concept","I-Concept","I-Concept","O"],"tokens":["los","m\u00e9dicos","diagnostican","talasemias","mediante","pruebas","de","sangre","."]}
{"ner_tags":["O","O","B-Concept","O","B-Concept","O","O","O","O","B-Concept","B-Action","O","O","B-Concept","O","B-Concept","O","B-Concept","O","B-Action","O","O","B-Concept","O","B-Concept","O","B-Concept","O"],"tokens":["en","las","personas","no","diab\u00e9ticas",",","las","causas","de","az\u00facar","baja","en","la","sangre","incluyen","medicamentos","o","enfermedades",",","problemas","con","las","hormonas","o","enzimas","y","tumores","."]}
{"ner_tags":["O","B-Concept","O","O","O","B-Concept","O","B-Action","B-Concept","O"],"tokens":["otros","problemas","surgen","cuando","las","plaquetas","no","funcionan","bien","."]}
{"ner_tags":["O","B-Concept","O","B-Concept","O","B-Concept","B-Predicate","O","B-Action","B-Concept","O","O","B-Concept","O","O","O","O","O","B-Action","B-Concept","O"],"tokens":["los","ni\u00f1os","sin","hogar","tienen","altos","\u00edndices","de","problemas","emocionales","y","de","conducta",",","con","frecuencia","por","haber","presenciado","abusos","."]}
{"ner_tags":["O","B-Reference","B-Concept","O","B-Action","O","O","B-Action","O","O","B-Action","O","B-Action","O","B-Concept","O"],"tokens":["cuando","\u00e9stas","c\u00e9lulas","se","da\u00f1an","o","se","enferman",",","se","afecta","la","producci\u00f3n","de","melanina","."]}
{"ner_tags":["O","B-Concept","O","B-Action","B-Concept","O","O","B-Concept","I-Concept","O","B-Action","B-Action","O","B-Concept","O"],"tokens":["su","m\u00e9dico","puede","encontrar","fibromas","durante","un","examen","ginecol\u00f3gico","o","utilizando","pruebas","de","imagen","."]}
{"ner_tags":["O","B-Reference","B-Concept","O","O","B-Predicate","O","B-Concept","O","B-Action","O","B-Concept","O","B-Action","O","B-Concept","O"],"tokens":["en","ese","caso",",","el","objetivo","del","tratamiento","es","mejorar","los","s\u00edntomas","y","aliviar","el","dolor","."]}
{"ner_tags":["O","B-Action","O","B-Action","O","O","B-Concept","O","O","O","B-Concept","O","O","O","B-Action","O","B-Concept","O","B-Action","O","B-Action","O","B-Predicate","O"],"tokens":["no","existe","una","cura","para","la","em",",","pero","las","medicinas","pueden","hacer","m\u00e1s","lento","el","proceso","y","ayudar","a","controlar","los","s\u00edntomas","."]}
{"ner_tags":["O","O","B-Concept","O","B-Action","B-Reference","O","O","O","B-Concept","O","B-Concept","B-Concept","O","B-Concept","O","B-Concept","I-Concept","O"],"tokens":["tiene","m\u00e1s","probabilidades","de","tener","uno","si","tiene","otras","enfermedades","como","miastenia","grave",",","lupus","o","artritis","reumatoide","."]}
{"ner_tags":["O","B-Concept","I-Concept","I-Concept","O","O","B-Concept","B-Action","O","B-Concept","O","O","B-Concept","I-Concept","O"],"tokens":["las","enfermedades","del","coraz\u00f3n","son","la","principal","causa","de","muerte","en","los","estados","unidos","."]}
{"ner_tags":["O","O","B-Action","O","B-Concept","B-Action","B-Predicate","B-Concept","O","B-Concept","O","O","B-Action","O","O","O","B-Predicate","I-Predicate","O","B-Concept","O"],"tokens":["usted","puede","bajar","de","peso","consumiendo","menos","calor\u00edas","y","grasas","y","haciendo","ejercicio","por","lo","menos","30","minutos","por","d\u00eda","."]}
{"ner_tags":["O","B-Concept","I-Concept","O","B-Action","O","B-Predicate","O","B-Concept","O","O","B-Concept","O"],"tokens":["demasiada","vitamina","d","tambi\u00e9n","eleva","el","nivel","de","calcio","en","su","sangre","."]}
{"ner_tags":["O","B-Concept","O","O","B-Action","O","O","B-Concept","B-Action","O","B-Predicate","O","B-Concept","I-Concept","B-Action","O","B-Concept","O"],"tokens":["los","p\u00f3lipos","pueden","ser","extirpados","cuando","un","m\u00e9dico","examina","el","interior","del","intestino","grueso","durante","una","colonoscop\u00eda","."]}
{"ner_tags":["O","O","B-Concept","I-Concept","I-Concept","O","O","O","B-Concept","B-Predicate","B-Concept","O","O","B-Concept","O"],"tokens":["el","c\u00e1ncer","de","pulm\u00f3n","es","uno","de","los","c\u00e1nceres","m\u00e1s","comunes","en","el","mundo","."]}
{"ner_tags":["O","B-Concept","O","B-Action","O","O","B-Predicate","O","B-Concept","O","O","O","B-Concept","O","O","B-Predicate","O","B-Concept","O","O","O","O","B-Concept","O","O","B-Concept","O"],"tokens":["la","gangrena","puede","ocurrir","en","la","superficie","del","cuerpo",",","como","la","piel","o","al","interior","del","cuerpo",",","como","en","los","m\u00fasculos","o","los","\u00f3rganos","."]}
{"ner_tags":["O","B-Concept","I-Concept","B-Action","O","O","O","B-Concept","B-Action","O","O","B-Concept","B-Action","B-Concept","O","B-Action","O"],"tokens":["el","sistema","inmunitario","ayuda","a","que","su","cuerpo","luche","contra","los","g\u00e9rmenes","produciendo","sustancias","para","combatirlos","."]}
{"ner_tags":["O","O","B-Concept","O","O","B-Concept","B-Action","O","B-Concept","O","O","B-Concept","I-Concept","B-Action","B-Concept","O","B-Predicate","O","O","B-Concept","O","B-Concept","I-Concept","I-Concept","O"],"tokens":["cuando","el","est\u00f3mago","y","el","intestino","digieren","los","alimentos",",","la","ves\u00edcula","biliar","libera","bilis","a","trav\u00e9s","de","un","tubo","denominado","conducto","biliar","com\u00fan","."]}
{"ner_tags":["O","B-Concept","O","B-Concept","O","B-Concept","O","B-Concept","I-Concept","O","B-Concept","I-Concept","O","B-Concept","I-Concept","I-Concept","O"],"tokens":["el","tratamiento","incluye","medicinas",",","aparatos","y","terapia","f\u00edsica",",","terapia","ocupacional","y","terapia","del","habla","."]}
{"ner_tags":["O","B-Action","B-Concept","B-Concept","I-Concept","I-Concept","O","O","O","B-Action","O","B-Reference","O"],"tokens":["el","acceso","limitado","a","la","atenci\u00f3n","de","salud","puede","empeorar","las","cosas","."]}
{"ner_tags":["B-Reference","B-Concept","O","O","O","O","O","O","B-Concept","O"],"tokens":["estos","g\u00e9rmenes","a","menudo","se","encuentran","en","la","naturaleza","."]}
{"ner_tags":["O","B-Concept","I-Concept","I-Concept","O","B-Predicate","O","B-Concept","B-Action","O","B-Action","O","O","B-Concept","B-Concept","O","B-Predicate","B-Concept","O"],"tokens":["las","\u00falceras","por","presi\u00f3n","son","\u00e1reas","de","piel","lesionada","por","permanecer","en","una","misma","posici\u00f3n","durante","demasiado","tiempo","."]}
{"ner_tags":["B-Reference","B-Concept","B-Action","O","O","B-Concept","O","O","B-Concept","I-Concept","O","O","B-Predicate","O","O","B-Concept","O"],"tokens":["estos","hongos","viven","en","el","suelo","de","las","zonas","\u00e1ridas","como","el","suroeste","de","los","ee.uu","."]}
{"ner_tags":["O","O","B-Action","B-Concept","O","B-Action","O","B-Action","O","O","B-Predicate","O","B-Concept","I-Concept","O","B-Action","O"],"tokens":["si","est\u00e1","tomando","anticoagulantes",",","necesita","tener","cuidado","con","la","cantidad","de","vitamina","k","que","consume","."]}
{"ner_tags":["O","B-Concept","O","O","B-Concept","O","O","O","O","B-Concept","O","O","O","B-Concept","B-Concept","O","O","O","O","O","B-Concept","O"],"tokens":["el","az\u00facar","en","la","sangre",",","tambi\u00e9n","llamada","``","glucosa","''","es","el","az\u00facar","principal","que","se","encuentra","en","su","sangre","."]}
{"ner_tags":["O","B-Concept","I-Concept","O","B-Concept","O","O","B-Action","O","O","B-Concept","I-Concept","O","O","B-Concept","O","B-Concept","O","B-Concept","O"],"tokens":["los","incendios","forestales","son","fuegos","fuera","de","control","en","un","\u00e1rea","natural",",","como","bosques",",","pastizales","o","praderas","."]}
{"ner_tags":["O","B-Concept","O","O","B-Predicate","B-Predicate","O","B-Concept","O","O","B-Concept","O","B-Concept","O","O","B-Concept","O","B-Concept","I-Concept","O","B-Concept","B-Concept","I-Concept","O"],"tokens":["las","personas","que","tienen","m\u00e1s","riesgo","de","apnea","son",":","hombres",",","personas","que","tienen","sobrepeso",",","historia","familiar","o","peque\u00f1as","v\u00edas","respiratorias","."]}
{"ner_tags":["O","B-Concept","O","O","O","B-Concept","O","O","B-Concept","O","O","B-Concept","B-Predicate","I-Predicate","O","B-Concept","O","O","B-Action","O","B-Concept","O"],"tokens":["el","ars\u00e9nico","forma","parte","del","aire",",","el","agua","y","la","tierra","a","trav\u00e9s","del","polvo","que","se","lleva","el","viento","."]}
{"ner_tags":["O","B-Reference","B-Action","O","B-Concept","O","O","O","B-Action","B-Concept","O"],"tokens":["si","usted","experimenta","un","desastre",",","es","normal","sentirse","estresado","."]}
{"ner_tags":["O","O","O","O","O","O","O","B-Concept","I-Concept","I-Concept","I-Concept","I-Concept","I-Concept","O","O","B-Concept","O","B-Action","O","B-Concept","O"],"tokens":["como","su","nombre","lo","indica",",","la","enfermedad","del","h\u00edgado","graso","por","alcohol","se","debe","al","alto","consumo","de","alcohol","."]}
{"ner_tags":["O","B-Action","O","B-Concept","O","B-Action","O","B-Concept","I-Concept","B-Concept","O"],"tokens":["no","existe","un","tratamiento","que","restablezca","la","funci\u00f3n","ov\u00e1rica","normal","."]}
{"ner_tags":["O","O","O","B-Concept","I-Concept","I-Concept","O","O","O","B-Reference","B-Predicate","O","B-Concept","O"],"tokens":["si","tiene","un","trastorno","del","movimiento",",","usted","experimenta","estos","tipos","de","alteraciones","."]}
{"ner_tags":["B-Reference","B-Concept","O","O","B-Concept","I-Concept","I-Concept","O","O","B-Concept","O","O","B-Concept","O","O","B-Predicate","O"],"tokens":["ese","conducto",",","llamado","t\u00fanel","del","carpo",",","contiene","tendones","y","un","nervio","en","el","interior","."]}
{"ner_tags":["O","B-Concept","I-Concept","I-Concept","O","B-Action","O","B-Reference","B-Action","O","B-Concept","I-Concept","O"],"tokens":["un","an\u00e1lisis","de","sangre","puede","mostrar","si","usted","tiene","el","virus","chikungunya","."]}
{"ner_tags":["O","B-Concept","B-Action","O","B-Concept","B-Action","O","O","B-Concept","I-Concept","I-Concept","O","B-Concept","I-Concept","O","B-Concept","O","B-Concept","I-Concept","I-Concept","O","B-Concept","I-Concept","I-Concept","O"],"tokens":["el","doctor","diagnosticar\u00e1","la","endocarditis","bas\u00e1ndose","en","sus","factores","de","riesgo",",","historia","cl\u00ednica",",","s\u00edntomas","y","ex\u00e1menes","del","coraz\u00f3n","y","ex\u00e1menes","de","laboratorio","."]}
{"ner_tags":["B-Action","B-Concept","O","O","O","B-Concept","O","O","B-Concept","B-Action","O","B-Concept","O"],"tokens":["prevenir","incendios","es","una","parte","importante","de","la","seguridad","contra","los","incendios","."]}
{"ner_tags":["O","B-Concept","I-Concept","O","O","B-Concept","O","B-Action","B-Concept","I-Concept","O","B-Action","O","B-Concept","O","B-Concept","O","B-Predicate","O","O","B-Concept","O"],"tokens":["la","escanograf\u00eda","nuclear","(","o","gammagraf\u00eda",")","utiliza","material","radioactivo","para","observar","las","estructuras","y","funciones","al","interior","de","su","cuerpo","."]}
{"ner_tags":["O","B-Concept","I-Concept","O","B-Action","B-Predicate","O","O","B-Concept","O"],"tokens":["el","c\u00e1ncer","uterino","suele","ocurrir","despu\u00e9s","de","la","menopausia","."]}
{"ner_tags":["B-Predicate","O","B-Concept","B-Predicate","O","B-Concept","I-Concept","O","B-Predicate","O","O","B-Action","O","O","B-Concept","I-Concept","O"],"tokens":["todos","los","ni\u00f1os","menores","de","cinco","a\u00f1os","de","edad","deben","ser","vacunados","con","la","vacuna","hib","."]}
{"ner_tags":["O","O","B-Concept","O","B-Action","O","O","B-Concept","I-Concept","B-Action","B-Action","O","B-Concept","O"],"tokens":["cuando","un","\u00e1rea","se","infecta",",","el","sistema","inmunitario","intenta","combatir","la","infecci\u00f3n","."]}
{"ner_tags":["O","B-Concept","I-Concept","O","O","B-Concept","B-Action","O","B-Concept","O","O","O","O","O","B-Concept","O"],"tokens":["la","m\u00e9dula","\u00f3sea","y","el","timo","producen","las","c\u00e9lulas","que","se","encuentran","en","la","linfa","."]}
{"ner_tags":["O","O","O","O","B-Concept","O","O","B-Concept","O","B-Concept","O","B-Concept","O","B-Concept","O","B-Concept","I-Concept","O"],"tokens":["las","partes","de","su","garganta","se","llaman","orofaringe",",","hipofaringe",",","nasofaringe","y","laringe","o","caja","lar\u00edngea","."]}
{"ner_tags":["B-Concept","O","O","O","O","B-Predicate","O","B-Concept","O","B-Action","O","B-Concept","B-Action","B-Predicate","O","B-Reference","O"],"tokens":["en","la","endometriosis",",","el","tipo","de","tejido","que","recubre","el","\u00fatero","crece","fuera","de","\u00e9ste","."]}
{"ner_tags":["B-Predicate","B-Concept","O","O","O","O","B-Concept","O","B-Action","O","B-Reference","B-Concept","O"],"tokens":["ciertos","genes","pueden","hacer","a","las","personas","m\u00e1s","propensas","a","estas","erupciones","."]}
{"ner_tags":["O","B-Concept","O","B-Action","O","B-Concept","O","O","O","B-Concept","O","O","B-Concept","O"],"tokens":["las","escuelas","pueden","tener","un","efecto","importante","en","la","salud","de","los","ni\u00f1os","."]}
{"ner_tags":["O","O","O","O","B-Concept","I-Concept","O","O","B-Action","O","B-Concept","O","B-Concept","O"],"tokens":["otro","tipo","es","la","aspergilosis","invasiva",",","que","da\u00f1a","los","tejidos","del","cuerpo","."]}
{"ner_tags":["O","B-Concept","O","O","O","O","O","O","B-Action","O","B-Action","B-Concept","O","B-Predicate","O","O","B-Concept","O","B-Action","O","O","B-Concept","B-Action","O","B-Concept","B-Concept","O"],"tokens":["las","personas","a","quienes","se","les","hace","un","trasplante","deben","tomar","medicamentos","el","resto","de","sus","vidas","para","impedir","que","sus","cuerpos","rechacen","el","p\u00e1ncreas","nuevo","."]}
{"ner_tags":["B-Concept","B-Concept","O","O","B-Action","O","O","O","O","B-Predicate","B-Concept","O","O","B-Concept","O"],"tokens":["boca","seca","es","la","sensaci\u00f3n","de","que","no","hay","suficiente","saliva","en","su","boca","."]}
{"ner_tags":["O","B-Concept","I-Concept","I-Concept","O","O","O","O","B-Concept","O","B-Action","O","B-Concept","O","O","B-Concept","O"],"tokens":["los","ataques","isqu\u00e9micos","transitorios","se","producen","cuando","la","sangre","no","llega","al","cerebro","por","unos","instantes","."]}
{"ner_tags":["O","B-Reference","B-Concept","B-Concept","B-Action","O","B-Concept","O","O","O","O","O","O","B-Concept","O"],"tokens":["cuando","estas","c\u00e9lulas","adicionales","forman","una","masa",",","se","les","conoce","como","un","tumor","."]}
{"ner_tags":["O","O","B-Predicate","B-Concept","O","O","B-Concept","O","O","O","B-Action","O","B-Concept","O"],"tokens":["si","tiene","bajos","niveles","de","determinadas","vitaminas",",","puede","tener","problemas","de","salud","."]}
{"ner_tags":["B-Action","O","B-Concept","I-Concept","O","O","O","B-Concept","I-Concept","I-Concept","I-Concept","O","O","O","B-Concept","O"],"tokens":["obtener","demasiada","vitamina","d","(","conocida","como","toxicidad","por","vitamina","d",")","puede","ser","perjudicial","."]}
{"ner_tags":["O","B-Concept","B-Concept","O","B-Concept","O","B-Concept","I-Concept","I-Concept","B-Concept","O"],"tokens":["cada","grupo","racial","o","\u00e9tnico","tiene","problemas","de","salud","espec\u00edficos","."]}
{"ner_tags":["O","B-Predicate","B-Concept","O","O","O","B-Concept","O","B-Action","O","B-Concept","O"],"tokens":["hay","tres","formas","en","que","las","personas","se","infectan","con","\u00e1ntrax","."]}
{"ner_tags":["O","B-Concept","O","B-Action","O","O","B-Predicate","O","B-Concept","O","B-Concept","O","B-Concept","O"],"tokens":["el","plomo","puede","afectar","a","casi","todos","los","\u00f3rganos","y","sistemas","del","cuerpo","."]}
{"ner_tags":["B-Reference","O","B-Action","O","B-Concept","O"],"tokens":["esto","deber\u00eda","reducir","su","dolor","."]}
{"ner_tags":["B-Predicate","B-Concept","O","B-Concept","I-Concept","B-Reference","B-Action","O"],"tokens":["muchos","beb\u00e9s","de","cuatro","meses","la","padecen","."]}
{"ner_tags":["O","B-Concept","O","O","O","B-Action","O","B-Action","O","O","B-Concept","O"],"tokens":["los","ni\u00f1os","no","deben","ser","castigados","por","orinarse","en","la","cama","."]}
{"ner_tags":["O","B-Predicate","B-Concept","O","B-Action","O","B-Action","O","B-Concept","O","O","B-Action","O"],"tokens":["el","primer","paso","del","tratamiento","es","reducir","el","dolor","y","la","hinchaz\u00f3n","."]}
{"ner_tags":["B-Concept","O","O","B-Concept","O","O","B-Concept","I-Concept","B-Action","B-Concept","B-Concept","O","O","B-Action","O","O","O","O","B-Predicate","O","B-Concept","O","B-Concept","O","B-Concept","O","B-Concept","O","B-Concept","O","B-Concept","I-Concept","O"],"tokens":["actualmente",",","los","ni\u00f1os","en","los","estados","unidos","reciben","vacunas","rutinariamente","que","los","protegen","de","m\u00e1s","de","una","docena","de","enfermedades","como","sarampi\u00f3n",",","polio",",","t\u00e9tanos",",","difteria","y","tos","ferina","."]}
{"ner_tags":["O","B-Predicate","B-Predicate","O","B-Reference","B-Concept","O","O","B-Concept","O"],"tokens":["el","mayor","riesgo","de","esta","condici\u00f3n","es","una","hemorragia","."]}
{"ner_tags":["O","B-Action","B-Concept","O","B-Concept","O","O","O","O","B-Action","O","B-Concept","O"],"tokens":["el","abuso","sexual","de","menores","es","una","forma","de","maltrato","al","menor","."]}
{"ner_tags":["B-Predicate","O","O","B-Concept","B-Predicate","O","B-Concept","O","B-Action","O","B-Concept","O","O","O","O","B-Concept","I-Concept","I-Concept","O","B-Concept","B-Concept","O","O","B-Action","O","B-Action","O","O","B-Action","B-Concept","O"],"tokens":["muchos","de","los","principales","riesgos","de","salud","que","enfrentan","los","hombres",",","como","el","de","c\u00e1ncer","del","colon","o","enfermedades","cardiacas",",","pueden","prevenirse","y","tratarse","con","un","diagn\u00f3stico","anticipado","."]}
{"ner_tags":["O","O","O","B-Concept","O","O","B-Action","B-Action","O","B-Concept","O","B-Action","O","B-Action","O"],"tokens":["aunque","puede","ser","molesta",",","la","tos","ayuda","al","cuerpo","a","curarse","o","protegerse","."]}
{"ner_tags":["O","O","B-Action","B-Concept","O","O","O","O","B-Predicate","O","O","B-Concept","O","O","B-Concept","B-Action","B-Concept","B-Concept","O"],"tokens":["si","piensa","someterse","a","un","aborto",",","la","mayor\u00eda","de","los","profesionales","de","la","salud","sugieren","asesor\u00eda","psicol\u00f3gica","."]}
{"ner_tags":["O","B-Action","O","B-Concept","I-Concept","O","O","B-Concept","O","B-Concept","O","B-Concept","O"],"tokens":["otros","problemas","del","sistema","linf\u00e1tico","pueden","incluir","infecciones",",","bloqueos","y","c\u00e1ncer","."]}
{"ner_tags":["O","B-Concept","I-Concept","O","B-Reference","B-Concept","O","O","B-Action","O","O","B-Action","O","O","B-Action","O","B-Action","O","B-Predicate","O","O","B-Concept","O"],"tokens":["las","sustancias","t\u00f3xicas","en","estos","productos","pueden","causar","da\u00f1o","si","se","inhalan",",","se","ingieren","o","absorben","a","trav\u00e9s","de","la","piel","."]}
{"ner_tags":["O","O","O","B-Action","O","B-Concept","O","B-Concept","O","B-Concept","B-Concept","O","B-Action","O","O","B-Concept","O","B-Concept","B-Concept","O","O","O","B-Concept","O","O","O","B-Action","O","O","B-Concept","O"],"tokens":["es","posible","que","necesite","una","cirug\u00eda","de","nuevo","si","bloqueos","posteriores","se","forman","en","las","arterias","o","venas","injertadas","o","en","las","arterias","que","no","estaban","bloqueadas","en","el","pasado","."]}
{"ner_tags":["O","B-Concept","B-Action","O","B-Predicate","O","B-Concept","O","O","O","B-Concept","O","O","O","B-Predicate","O","O","B-Concept","O","O","B-Action","O","O","B-Action","O","O","B-Concept","O"],"tokens":["los","ri\u00f1ones","controlan","la","cantidad","de","sodio","presente","en","el","cuerpo",";","si","tiene","demasiado","y","los","ri\u00f1ones","no","pueden","eliminarlo",",","se","acumula","en","la","sangre","."]}
{"ner_tags":["O","B-Concept","O","B-Action","O","B-Concept","O","O","B-Concept","O","B-Concept","O","B-Concept","O"],"tokens":["los","antibi\u00f3ticos","pueden","tratar","las","ets","causadas","por","bacterias",",","hongos","o","par\u00e1sitos","."]}
{"ner_tags":["B-Concept","I-Concept","I-Concept","B-Concept","O","O","B-Action","O","B-Action","O","B-Action","O","B-Concept","O","B-Action","B-Concept","B-Action","O","B-Concept","O"],"tokens":["medidas","de","seguridad","adecuadas","en","la","manipulaci\u00f3n",",","cocci\u00f3n","y","almacenamiento","de","alimentos","pueden","prevenir","enfermedades","transmitidas","por","alimentos","."]}
{"ner_tags":["B-Action","B-Concept","B-Concept","O","B-Concept","I-Concept","O"],"tokens":["contiene","c\u00e9lulas","inmaduras","llamadas","c\u00e9lulas","madre","."]}
{"ner_tags":["O","B-Concept","O","B-Concept","O","B-Action","O","B-Action","O","B-Action","O","B-Concept","O","B-Concept","O","B-Concept","O","O","O","B-Concept","O","B-Concept","O"],"tokens":["los","analg\u00e9sicos","son","medicinas","que","reducen","o","alivian","los","dolores","de","cabeza",",","musculares",",","artr\u00edticos","o","muchos","otros","achaques","y","dolores","."]}
{"ner_tags":["O","B-Concept","O","O","O","B-Concept","O","B-Concept","O","O","B-Concept","O","O","O","B-Concept","O"],"tokens":["la","diabetes","significa","que","la","glucosa","o","az\u00facar","en","su","sangre",",","es","demasiado","alta","."]}
{"ner_tags":["O","B-Concept","B-Action","B-Concept","B-Concept","O","B-Concept","O"],"tokens":["los","test\u00edculos","producen","hormonas","masculinas","y","semen","."]}
{"ner_tags":["O","B-Action","O","B-Concept","O","O","B-Concept","B-Action","O","B-Action","B-Concept","O"],"tokens":["el","consumo","del","tabaco","es","la","principal","causa","de","muerte","prevenible","."]}
{"ner_tags":["O","B-Concept","I-Concept","I-Concept","B-Concept","O","B-Action","B-Predicate","O","B-Action","O","B-Predicate","I-Predicate","O","B-Concept","O"],"tokens":["el","trabajo","de","parto","prematuro","puede","comenzar","antes","de","completar","las","37","semanas","de","embarazo","."]}
{"ner_tags":["O","O","B-Action","O","B-Action","O","O","B-Action","O","O","B-Concept","O"],"tokens":["no","se","conoce","la","causa","de","los","trastornos","de","la","personalidad","."]}
{"ner_tags":["O","O","B-Action","B-Concept","O","B-Concept","O","O","B-Action","O","B-Concept","O","O","B-Action","B-Concept","I-Concept","O","B-Action","O","O","O","O","B-Concept","O"],"tokens":["las","tres","causas","principales","de","anemia","son",":","p\u00e9rdida","de","sangre",",","no","producir","gl\u00f3bulos","rojos","y","destrucci\u00f3n","de","estos","a","gran","velocidad","."]}
{"ner_tags":["O","O","O","O","B-Concept","I-Concept","I-Concept","I-Concept","O","O","O","B-Concept","I-Concept","I-Concept","O","O","B-Concept","I-Concept","I-Concept","O","O","O","B-Concept","I-Concept","O","B-Concept","O","B-Action","O","O","B-Action","O","B-Concept","O","B-Concept","O"],"tokens":["por","ejemplo",",","las","enfermedades","de","los","nervios",",","como","la","neuralgia","del","trig\u00e9mino","o","la","par\u00e1lisis","de","bell","a","veces","causan","dolor","facial",",","espasmos","y","problemas","con","los","movimientos","del","ojo","o","faciales","."]}
{"ner_tags":["O","B-Concept","O","B-Action","O","O","B-Action","B-Concept","O","B-Concept","O","B-Concept","O","B-Concept","O"],"tokens":["como","adolescente",",","pasas","por","muchos","cambios","f\u00edsicos",",","mentales",",","emocionales","y","sociales","."]}
{"ner_tags":["B-Reference","O","O","B-Concept","I-Concept","I-Concept","O","B-Concept","O","B-Concept","I-Concept","O"],"tokens":["esto","puede","provocar","dolor","p\u00e9lvico","cr\u00f3nico",",","infertilidad","y","embarazo","ect\u00f3pico","."]}
{"ner_tags":["B-Concept","O","O","O","O","O","B-Predicate","O","B-Concept","O","O","O","O","O","O","B-Concept","O","B-Action","O","B-Concept","O","O","B-Concept","O","O","B-Concept","O","O","B-Concept","I-Concept","O"],"tokens":["haemophilus","es","el","nombre","de","un","grupo","de","bacterias","que","pueden","causar","diferentes","tipos","de","enfermedades","que","involucran","la","respiraci\u00f3n",",","los","huesos",",","las","articulaciones","y","el","sistema","nervioso","."]}
{"ner_tags":["O","B-Action","O","B-Action","B-Concept","I-Concept","B-Concept","I-Concept","B-Predicate","O","O","B-Concept","O"],"tokens":["el","dolor","puede","comenzar","uno","o","dos","d\u00edas","antes","de","su","per\u00edodo","."]}
{"ner_tags":["B-Action","O","B-Concept","O","O","O","B-Predicate","O","B-Concept","I-Concept","I-Concept","I-Concept","O","O","B-Concept","B-Concept","O","O","B-Action","O","B-Action","O","B-Concept","O"],"tokens":["bajar","de","peso","(","por","lo","menos","del","5","al","10","%","de","su","peso","actual",")","puede","prevenir","o","retrasar","la","diabetes","."]}
{"ner_tags":["B-Reference","B-Concept","B-Action","O","O","B-Concept","I-Concept","B-Action","O","B-Concept","I-Concept","O","B-Action","O","B-Predicate","O","B-Concept","O"],"tokens":["estos","estudios","demostraron","que","la","dieta","dash","baja","la","presi\u00f3n","arterial","y","mejora","los","niveles","de","colesterol","."]}
{"ner_tags":["O","B-Concept","O","O","O","O","B-Action","O","B-Action","B-Concept","O","B-Action","O","B-Concept","O","B-Concept","O"],"tokens":["la","piel","tambi\u00e9n","se","hace","m\u00e1s","delgada","y","pierde","grasa",",","torn\u00e1ndose","menos","suave","y","lisa","."]}
{"ner_tags":["B-Reference","B-Concept","O","B-Action","B-Predicate","O","O","B-Concept","I-Concept","I-Concept","O"],"tokens":["estos","s\u00edntomas","suelen","desaparecer","despu\u00e9s","de","un","par","de","d\u00edas","."]}
{"ner_tags":["B-Predicate","B-Concept","I-Concept","I-Concept","O","B-Action","O","B-Action","O","B-Concept","O"],"tokens":["varios","ex\u00e1menes","de","laboratorio","pueden","confirmar","el","diagn\u00f3stico","de","ebola","."]}
{"ner_tags":["B-Concept","I-Concept","O","B-Action","O","B-Concept","O","O","B-Concept","O"],"tokens":["la","lactancia","materna","ofrece","muchos","beneficios","para","su","beb\u00e9","."]}
{"ner_tags":["B-Reference","B-Action","B-Concept","O","O","O","B-Concept","O","O","O","B-Action","B-Predicate","O","B-Concept","O","B-Predicate","O","B-Concept","O","B-Concept","O"],"tokens":["estas","producen","saliva",",","tambi\u00e9n","llamada","esputo",",","y","la","segregan","hacia","la","boca","a","trav\u00e9s","de","aberturas","llamadas","ductos","."]}
{"ner_tags":["O","B-Concept","O","O","B-Action","O","B-Concept","O","B-Action","B-Concept","I-Concept","O","B-Concept","O","B-Predicate","O","O","B-Concept","O","B-Action","O"],"tokens":["la","persona","que","est\u00e1","sufriendo","un","paro","deber\u00eda","recibir","resucitaci\u00f3n","cardiopulmonar","(","rcp",")","hasta","que","la","desfibrilaci\u00f3n","est\u00e9","disponible","."]}
{"ner_tags":["O","O","O","O","B-Action","B-Concept","O","B-Reference","B-Concept","O"],"tokens":["a","veces",",","pueden","surgir","problemas","en","este","proceso","."]}
{"ner_tags":["O","B-Concept","I-Concept","I-Concept","O","B-Action","B-Predicate","O","O","B-Action","O"],"tokens":["las","crisis","por","c\u00e1lculos","suelen","presentarse","despu\u00e9s","de","las","comidas","."]}
{"ner_tags":["O","B-Concept","O","O","O","O","B-Concept","I-Concept","O"],"tokens":["la","depresi\u00f3n","es","una","parte","del","trastorno","bipolar","."]}
{"ner_tags":["O","O","B-Action","B-Action","B-Concept","O","O","B-Concept","O","B-Concept","O","O"],"tokens":["no","se","debe","utilizar","botox","durante","el","embarazo","o","la","lactancia","."]}
{"ner_tags":["O","B-Concept","B-Action","O","B-Concept","B-Action","O","B-Concept","O"],"tokens":["las","superficies","presionan","la","mama","haci\u00e9ndola","m\u00e1s","plana","."]}
{"ner_tags":["O","B-Action","B-Concept","O","B-Action","O","O","B-Concept","O","O","B-Concept","I-Concept","O","O","B-Concept","I-Concept","I-Concept","I-Concept","O"],"tokens":["si","necesitas","ayuda",",","habla","con","tus","padres",",","un","consejero","escolar","o","un","profesional","de","la","salud","."]}
{"ner_tags":["O","B-Concept","O","B-Action","B-Concept","O"],"tokens":["las","verrugas","pueden","desaparecer","espont\u00e1neamente","."]}
{"ner_tags":["O","B-Reference","O","B-Action","O","O","O","O","O","B-Action","O"],"tokens":["si","eso","no","funciona",",","es","posible","que","necesite","cirug\u00eda","."]}
{"ner_tags":["O","B-Action","B-Concept","B-Concept","O","B-Action","O","B-Concept","B-Predicate","O","B-Concept","O","B-Concept","I-Concept","O","B-Action","B-Concept","O","O","B-Action","O"],"tokens":["para","mantener","huesos","resistentes",",","consuma","una","dieta","rica","en","calcio","y","vitamina","d",",","practique","ejercicios","y","no","fume","."]}
{"ner_tags":["B-Predicate","B-Concept","O","O","B-Predicate","O","B-Concept","I-Concept","I-Concept","O"],"tokens":["muchas","personas","est\u00e1n","en","riesgo","de","diabetes","tipo","2","."]}
{"ner_tags":["O","B-Concept","O","O","O","B-Action","O","B-Concept","I-Concept","I-Concept","B-Action","O","O","B-Concept","I-Concept","O"],"tokens":["el","tratamiento","principal","es","la","inyecci\u00f3n","del","factor","de","coagulaci\u00f3n","faltante","en","el","torrente","sangu\u00edneo","."]}
{"ner_tags":["O","B-Action","O","O","B-Predicate","O","B-Concept","I-Concept","I-Concept","O","O","O","B-Concept","B-Concept","O"],"tokens":["el","tratamiento","para","algunos","tipos","de","c\u00e1ncer","de","garganta","tambi\u00e9n","puede","incluir","terapia","dirigida","."]}
{"ner_tags":["O","B-Concept","I-Concept","I-Concept","B-Action","O","O","O","B-Concept","I-Concept","O","B-Predicate","I-Predicate","O","O","B-Concept","O","O","B-Predicate","O","B-Concept","O","B-Predicate","O","B-Concept","I-Concept","O"],"tokens":["el","c\u00e1ncer","de","est\u00f3mago","afecta","principalmente","a","las","personas","mayores",",","dos","tercios","de","las","personas","con","este","tipo","de","c\u00e1ncer","es","mayor","de","65","a\u00f1os","."]}
{"ner_tags":["O","B-Concept","O","B-Action","O","B-Predicate","B-Concept","B-Concept","O","O","B-Concept","O"],"tokens":["la","mu\u00f1eca","est\u00e1","formada","por","ocho","huesos","peque\u00f1os","conocidos","como","carpianos","."]}
{"ner_tags":["O","B-Concept","I-Concept","O","O","O","B-Predicate","O","O","B-Concept","O"],"tokens":["las","gl\u00e1ndulas","suprarrenales","se","localizan","justo","arriba","de","los","ri\u00f1ones","."]}
{"ner_tags":["B-Reference","B-Concept","O","O","B-Action","O","B-Concept","B-Concept","O","O","B-Concept","O"],"tokens":["estos","problemas","causan","una","acumulaci\u00f3n","de","sustancias","nocivas","en","su","cuerpo","."]}
{"ner_tags":["O","B-Concept","O","B-Concept","B-Action","O","B-Concept","O","O","B-Concept","B-Concept","O","O","B-Concept","O"],"tokens":["las","ampollas","son","sacos","llenos","de","l\u00edquido","en","la","capa","externa","de","la","piel","."]}
{"ner_tags":["O","B-Concept","O","B-Concept","O","O","O","O","O","O","O","B-Concept","O","O","O","O","O","O","O","O","B-Concept","B-Concept","O","O","O","O","B-Concept","O","O","B-Action","B-Predicate","O","O","B-Concept","O","B-Concept","O","B-Concept","O","O","O","O","O","O","O","B-Concept","O","O","O","O","O","O","O"],"tokens":["la","fenilcetonuria","(","pku",",","por","sus","siglas","en","ingl\u00e9s","y","fcu","por","sus","siglas","en","espa\u00f1ol",")","es","un","trastorno","gen\u00e9tico","en","el","cual","el","organismo","no","puede","procesar","parte","de","una","prote\u00edna","llamada","fenilalanina","(","phe",",","por","sus","siglas","en","ingl\u00e9s","y","pah","por","sus","siglas","en","espa\u00f1ol",")","."]}
{"ner_tags":["O","B-Concept","I-Concept","I-Concept","B-Concept","O","B-Action","B-Predicate","O","B-Concept","I-Concept","I-Concept","I-Concept","O"],"tokens":["el","estado","de","coma","rara","vez","dura","m\u00e1s","de","2","a","4","semanas","."]}
{"ner_tags":["O","B-Concept","I-Concept","O","O","O","B-Concept","O","O","O","B-Concept","O","O","B-Concept","O"],"tokens":["la","hemorragia","gastrointestinal","no","es","una","enfermedad",",","sino","el","s\u00edntoma","de","una","enfermedad","."]}
{"ner_tags":["O","B-Concept","O","O","B-Concept","B-Action","B-Reference","B-Concept","B-Concept","O"],"tokens":["las","enfermedades","de","la","retina","afectan","este","importante","tejido","."]}
{"ner_tags":["O","B-Action","B-Action","O","B-Action","O","B-Concept","O","B-Concept","B-Concept","O","O","B-Action","O"],"tokens":["la","inflamaci\u00f3n","limita","el","flujo","de","sangre","hacia","\u00f3rganos","importantes","y","provoca","da\u00f1os","."]}
{"ner_tags":["O","B-Concept","O","O","O","O","B-Concept","O","B-Concept","O","B-Concept","O","O","B-Concept","I-Concept","O"],"tokens":["los","brazos","tambi\u00e9n","est\u00e1n","formados","por","m\u00fasculos",",","articulaciones",",","tendones","y","otros","tejidos","conectivos","."]}
{"ner_tags":["B-Predicate","O","B-Concept","I-Concept","B-Concept","I-Concept","O","O","B-Action","O","B-Predicate","B-Concept","O","O","B-Concept","B-Predicate","B-Concept","I-Concept","I-Concept","O","B-Action","O","B-Concept","I-Concept","I-Concept","O"],"tokens":["despu\u00e9s","de","15","a","20","a\u00f1os","de","la","aparici\u00f3n","del","primer","s\u00edntoma",",","las","personas","con","ataxia","de","freidreich","suelen","necesitar","una","silla","de","ruedas","."]}
{"ner_tags":["O","B-Concept","O","O","B-Concept","I-Concept","I-Concept","I-Concept","O","O","O","B-Concept","O"],"tokens":["la","s\u00edfilis","es","una","enfermedad","de","transmisi\u00f3n","sexual","causada","por","una","bacteria","."]}
{"ner_tags":["O","O","B-Concept","O","B-Concept","O","O","B-Concept","O","B-Action","B-Predicate","B-Concept","O"],"tokens":["cuando","las","mitocondrias","son","defectuosas",",","las","c\u00e9lulas","no","tienen","suficiente","energ\u00eda","."]}
{"ner_tags":["O","O","O","O","O","B-Concept","O","O","O","B-Concept","O","O","B-Action","O","O","O","B-Concept","O"],"tokens":["pero","existe","otro","tipo","de","esteroides",",","tambi\u00e9n","llamados","corticoides",",","que","trata","una","variedad","de","problemas","."]}
{"ner_tags":["O","O","B-Concept","B-Reference","B-Action","O","O","O","O","B-Concept","O","B-Action","B-Concept","B-Concept","O"],"tokens":["cuando","un","insecto","lo","pica",",","generalmente","en","el","rostro",",","deja","excrementos","infectados","."]}
{"ner_tags":["O","B-Concept","O","B-Action","O","O","B-Concept","B-Predicate","O","O","B-Concept","O"],"tokens":["las","chinches","se","esconden","en","varios","lugares","alrededor","de","la","cama","."]}
{"ner_tags":["O","O","O","B-Action","B-Concept","O","O","B-Concept","B-Concept","B-Action","O"],"tokens":["cada","vez","que","toma","antibi\u00f3ticos",",","las","bacterias","sensibles","mueren","."]}
{"ner_tags":["O","B-Concept","O","O","O","B-Concept","O","B-Action","B-Predicate","O","O","B-Action","O","B-Concept","O"],"tokens":["otros","\u00f3rganos",",","como","el","h\u00edgado",",","har\u00e1n","algunas","de","las","funciones","del","bazo","."]}
{"ner_tags":["O","B-Concept","B-Predicate","B-Action","O","B-Concept","O","B-Action","O","B-Concept","O"],"tokens":["las","mujeres","mayores","necesitan","mucho","calcio","para","prevenir","la","osteoporosis","."]}
{"ner_tags":["O","O","B-Reference","O","B-Concept","O","B-Concept","O","O","B-Action","O","O","B-Predicate","O","O","B-Concept","O","B-Action","O","B-Concept","O"],"tokens":["dos","de","ellos",",","uva","y","uvb",",","pueden","llegar","a","la","superficie","de","la","tierra","y","afectar","su","piel","."]}
{"ner_tags":["O","B-Concept","O","O","B-Action","O","O","O","O","O","B-Concept","O","B-Action","B-Concept","O","O","B-Action","B-Concept","B-Concept","O"],"tokens":["la","epilepsia","tiene","muchas","causas","posibles",",","que","incluyen","las","enfermedades",",","lesiones","cerebrales","y","el","desarrollo","cerebral","anormal","."]}
{"ner_tags":["O","B-Concept","I-Concept","I-Concept","I-Concept","I-Concept","O","O","O","B-Action","O","O","B-Action","O","O","B-Action","B-Concept","O"],"tokens":["un","trastorno","por","consumo","de","alcohol","consiste","en","la","angustia","y","el","da\u00f1o","que","causa","beber","alcohol","."]}
{"ner_tags":["O","B-Concept","O","O","B-Concept","B-Concept","O","O","B-Concept","O","B-Concept","B-Concept","O","B-Concept","O","B-Concept","O","B-Concept","O"],"tokens":["los","tratamientos","pueden","incluir","terapia","f\u00edsica","para","el","pecho",",","terapias","nutricionales","y","respiratorias",",","medicinas","y","ejercicio","."]}
{"ner_tags":["O","B-Reference","O","O","O","B-Concept","I-Concept","I-Concept","I-Concept","I-Concept","O","O","B-Action","B-Concept","O","O","B-Action","O","B-Concept","O"],"tokens":["a","esto","se","le","llama","enfermedad","de","las","arterias","coronarias","y","se","desarrolla","lentamente","con","el","transcurso","del","tiempo","."]}
{"ner_tags":["O","B-Concept","O","O","B-Concept","B-Concept","O","B-Action","B-Predicate","O","B-Action","O","O","O","B-Predicate","B-Concept","O","B-Concept","O"],"tokens":["los","beb\u00e9s","y","los","ni\u00f1os","peque\u00f1os","tambi\u00e9n","presentan","riesgos","de","ca\u00eddas",",","por","ejemplo","desde","muebles","y","escaleras","."]}
{"ner_tags":["O","B-Reference","O","B-Concept","O","B-Concept","I-Concept","I-Concept","I-Concept","O"],"tokens":["y","otros","causan","infecciones","llamadas","infecciones","por","micobacterias","at\u00edpicas","."]}
{"ner_tags":["O","B-Concept","B-Action","O","B-Concept","O","B-Action","O","B-Concept","I-Concept","O","O","O","O","B-Action","O","B-Action","O","O","O"],"tokens":["los","m\u00e9dicos","usan","la","ecocardiograf\u00eda","para","diagnosticar","muchos","problemas","card\u00edacos","diferentes",",","y","para","comprobar","lo","grave","que","son","."]}
{"ner_tags":["O","B-Concept","O","B-Action","O","O","O","O","O","O","O","O","B-Action","O","B-Concept","O","O","O","O","B-Concept","B-Concept","O","B-Action","O"],"tokens":["las","personas","con","delirio","a","menudo",",","aunque","no","siempre",",","se","recuperan","por","completo","despu\u00e9s","de","que","su","enfermedad","subyacente","sea","tratada","."]}
{"ner_tags":["O","B-Concept","O","B-Predicate","B-Concept","O","B-Concept","O","B-Concept","B-Concept","O","B-Concept","O","B-Concept","O","O","B-Concept","I-Concept","B-Concept","O"],"tokens":["la","deshidrataci\u00f3n","es","m\u00e1s","com\u00fan","en","beb\u00e9s",",","ni\u00f1os","peque\u00f1os",",","ancianos","y","personas","con","un","sistema","inmunitario","d\u00e9bil","."]}
{"ner_tags":["O","O","B-Concept","O","B-Concept","O","B-Action","O","O","B-Concept","O"],"tokens":["pero","los","traumatismos","provocan","hematomas","y","distensi\u00f3n","de","los","ligamentos","."]}
{"ner_tags":["O","O","B-Concept","I-Concept","I-Concept","O","O","O","B-Concept","O","O","B-Concept","O","B-Action","O","O","B-Action","B-Concept","O","B-Concept","O"],"tokens":["con","la","diabetes","tipo","2",",","la","m\u00e1s","com\u00fan",",","el","cuerpo","no","produce","o","no","usa","bien","la","insulina","."]}
{"ner_tags":["O","B-Reference","O","B-Action","O","O","B-Concept","O","O","B-Action","O","O","B-Concept","O"],"tokens":["si","esto","no","ocurre",",","el","\u00fatero",",","se","desprende","de","su","recubrimiento","."]}
{"ner_tags":["O","B-Concept","I-Concept","B-Action","O","B-Predicate","O","O","B-Action","O","B-Concept","O"],"tokens":["las","hormonas","tiroideas","controlan","el","ritmo","de","muchas","actividades","del","cuerpo","."]}
{"ner_tags":["O","O","O","O","B-Concept","B-Concept","O","B-Concept","O","B-Concept","I-Concept","O","B-Concept","O","B-Concept","O","B-Concept","O","B-Concept","O","B-Concept","O"],"tokens":["las","causas","de","las","hemorragias","anormales","incluyen","hormonas",",","problemas","tiroideos",",","fibromas",",","p\u00f3lipos",",","c\u00e1ncer",",","infecciones","o","embarazo","."]}
{"ner_tags":["O","B-Action","I-Action","I-Action","O","O","B-Concept","O","B-Concept","O","B-Predicate","B-Concept","O","O","B-Concept","O"],"tokens":["el","reemplazo","de","cadera","es","una","cirug\u00eda","para","personas","con","da\u00f1os","severos","en","la","cadera","."]}
{"ner_tags":["O","B-Concept","I-Concept","B-Action","B-Concept","O","B-Action","O","O","B-Concept","O","O","O","O","O","B-Predicate","O","B-Concept","I-Concept","O"],"tokens":["el","asesoramiento","gen\u00e9tico","ofrece","informaci\u00f3n","y","apoyo","a","las","personas","que","tienen","o","pueden","tener","riesgos","de","trastornos","gen\u00e9ticos","."]}
{"ner_tags":["O","O","B-Concept","B-Action","B-Concept","B-Predicate","O","B-Concept","O","O","O","O","O","B-Action","O","O","B-Concept","O","O","B-Concept","O","B-Action","O"],"tokens":["si","una","persona","inhala","altos","niveles","de","asbestos",",","con","el","tiempo","pueden","acumularse","en","los","pulmones","y","causar","cicatrices","e","inflamaci\u00f3n","."]}
{"ner_tags":["O","O","B-Action","O","B-Concept","O","B-Reference","B-Concept","O","B-Action","B-Concept","O","B-Concept","O"],"tokens":["si","se","detecta","a","tiempo",",","la","enfermedad","se","cura","f\u00e1cilmente","con","antibi\u00f3ticos","."]}
{"ner_tags":["O","B-Concept","I-Concept","O","O","B-Concept","I-Concept","I-Concept","O"],"tokens":["los","rayos","uvb","pueden","causar","quemaduras","de","sol","."]}
{"ner_tags":["O","B-Concept","O","B-Action","O","O","O","O","B-Action","I-Action","B-Predicate","B-Concept","O","O","B-Concept","B-Action","O"],"tokens":["el","vih","suele","contagiarse","a","trav\u00e9s","de","las","relaciones","sexuales","sin","protecci\u00f3n","con","una","persona","infectada","."]}
{"ner_tags":["B-Action","O","B-Concept","O","B-Concept","O","B-Action","B-Reference","B-Concept","O"],"tokens":["manipular","los","alimentos","con","cuidado","puede","prevenir","estas","enfermedades","."]}
{"ner_tags":["O","O","O","B-Action","O","B-Concept","B-Concept","O","B-Concept","O","B-Concept","O","B-Action","B-Concept","O","B-Action","O","B-Action","O","B-Concept","O","B-Action","O","B-Concept","O"],"tokens":["si","va","a","realizar","un","viaje","largo","en","autom\u00f3vil","o","avi\u00f3n",",","haga","pausas","para","caminar","o","estirar","las","piernas","e","ingiera","mucho","l\u00edquido","."]}
{"ner_tags":["O","B-Action","B-Predicate","O","B-Concept","I-Concept","O","B-Action","O","O","B-Concept","O","B-Action","O","B-Concept","O","O","O","B-Concept","O"],"tokens":["la","rehabilitaci\u00f3n","tras","un","accidente","cerebrovascular","puede","ayudar","a","las","personas","a","superar","las","discapacidades","causadas","por","la","apoplej\u00eda","."]}
{"ner_tags":["O","B-Action","O","B-Action","O","B-Action","I-Action","B-Concept","O","B-Action","O","B-Action","B-Reference","B-Concept","O"],"tokens":["la","observaci\u00f3n",",","tratamiento","y","cuidado","m\u00e9dico","regular","pueden","prevenir","o","manejar","estos","riesgos","."]}
{"ner_tags":["O","O","O","B-Reference","B-Concept","O","B-Action","O","O","B-Concept","O","O","B-Predicate","O","O","B-Concept","O","B-Action","B-Concept","O","B-Concept","O","B-Concept","O"],"tokens":["el","objetivo","de","estos","cuidados","es","ayudar","a","las","personas","que","est\u00e1n","cerca","de","la","muerte","a","tener","paz",",","comodidades","y","dignidad","."]}
{"ner_tags":["O","B-Action","O","O","B-Concept","I-Concept","O","O","B-Action","B-Predicate","O","O","O","B-Predicate","B-Concept","O","B-Action","B-Concept","I-Concept","O","O","O"],"tokens":["los","problemas","con","el","sistema","nasolagrimal","incluyen","la","producci\u00f3n","de","demasiadas","o","de","pocas","l\u00e1grimas","o","problemas","con","los","conductos","lagrimales","."]}
{"ner_tags":["O","B-Reference","O","B-Action","O","O","O","B-Concept","O","O","B-Predicate","O","B-Concept","O","O","B-Concept","O","O","B-Concept","B-Concept","O"],"tokens":["cuando","eso","no","ocurre",",","usted","tiene","hipoglicemia","y","el","nivel","de","az\u00facar","en","la","sangre","puede","estar","peligrosamente","bajo","."]}
{"ner_tags":["O","B-Concept","O","B-Action","B-Reference","B-Concept","O","O","B-Action","O","O","B-Concept","O","O","B-Predicate","B-Concept","O","O","O","B-Concept","O"],"tokens":["el","m\u00e9dico","puede","recomendarle","el","procedimiento","si","tiene","dolor","en","la","rodilla","y","si","otros","tratamientos","ya","no","son","efectivos","."]}
{"ner_tags":["B-Predicate","B-Concept","I-Concept","I-Concept","O","B-Action","O","B-Action","O","B-Concept","O","O","B-Concept","O","B-Concept","B-Predicate","O"],"tokens":["algunas","fases","del","sue\u00f1o","pueden","ayudarle","a","sentirse","m\u00e1s","descansado","y","con","energ\u00eda","al","d\u00eda","siguiente","."]}
{"ner_tags":["O","O","B-Action","O","B-Concept","B-Predicate","O","O","B-Predicate","O","B-Concept","O","O","O","O","B-Action","B-Concept","O"],"tokens":["pero","si","tiene","un","hdl","bajo","y","uno","alto","de","ldl",",","es","posible","que","necesite","medicamentos","."]}
{"ner_tags":["B-Reference","O","O","O","B-Concept","O","B-Action","O","O","B-Concept","O"],"tokens":["ellas","sirven","como","un","sistema","de","reparaci\u00f3n","para","el","organismo","."]}
{"ner_tags":["O","B-Predicate","O","B-Concept","B-Predicate","B-Concept","B-Action","B-Concept","O"],"tokens":["no","todas","las","personas","con","vih","desarrollan","sida","."]}
{"ner_tags":["O","O","B-Concept","I-Concept","I-Concept","O","B-Reference","O","O","O","B-Concept","O","B-Action","B-Predicate","B-Concept","O","O","O","B-Action","B-Concept","O","O","O","O","O","O","B-Action","O","O","B-Concept","O"],"tokens":["en","la","diabetes","tipo","2",",","esto","ocurre","porque","su","cuerpo","no","produce","suficiente","insulina","o","no","la","utiliza","bien",",","lo","que","se","conoce","como","resistencia","a","la","insulina","."]}
{"ner_tags":["O","B-Concept","I-Concept","I-Concept","O","B-Concept","I-Concept","I-Concept","O","O","O","O","O","B-Action","O","O","B-Action","B-Concept","I-Concept","O"],"tokens":["los","an\u00e1lisis","de","sangre","y","an\u00e1lisis","de","orina","son","la","\u00fanica","manera","de","saber","si","usted","tiene","enfermedad","renal","."]}
{"ner_tags":["O","B-Concept","I-Concept","I-Concept","O","O","B-Concept","O","B-Action","O","O","B-Concept","O","O","O","B-Concept","I-Concept","B-Concept","O","O","B-Predicate","O","O","B-Concept","O"],"tokens":["el","s\u00edndrome","de","klinefelter","es","un","cuadro","que","ocurre","entre","los","hombres","que","tienen","un","cromosoma","x","adicional","en","la","mayor\u00eda","de","sus","c\u00e9lulas","."]}
{"ner_tags":["O","B-Concept","O","O","B-Concept","O","O","O","O","B-Concept","O"],"tokens":["las","setas","y","el","moho","son","algunos","tipos","de","hongos","."]}
{"ner_tags":["O","O","B-Concept","O","O","B-Concept","O","O","O","O","O","B-Action","O","B-Concept","O"],"tokens":["pero","las","mujeres","y","los","adolescentes","tienen","la","mayor","cantidad","de","intentos","de","suicidio","."]}
{"ner_tags":["B-Predicate","B-Concept","O","B-Action","O","B-Concept","O","O","B-Action","O"],"tokens":["algunos","medicamentos","pueden","aliviar","los","s\u00edntomas","y","el","dolor","."]}
{"ner_tags":["O","B-Concept","O","O","O","B-Predicate","O","O","B-Predicate","O","O","B-Concept","O"],"tokens":["cada","ovario","tiene","aproximadamente","el","tama\u00f1o","y","la","forma","de","una","almendra","."]}
{"ner_tags":["O","B-Concept","I-Concept","O","O","O","O","B-Concept","B-Concept","O","O","B-Predicate","O","B-Concept","O"],"tokens":["las","convulsiones","generalizadas","son","el","resultado","de","actividades","anormales","en","ambos","lados","del","cerebro","."]}
{"ner_tags":["O","B-Concept","O","B-Concept","B-Concept","O","B-Action","B-Concept","I-Concept","O","O","B-Action","B-Concept","O","B-Action","O","B-Concept","I-Concept","I-Concept","O"],"tokens":["las","personas","con","enfermedades","respiratorias","pueden","recibir","rehabilitaci\u00f3n","pulmonar","para","poder","respirar","mejor","y","mejorar","su","calidad","de","vida","."]}
{"ner_tags":["O","O","B-Concept","B-Action","O","O","B-Concept","O","B-Action","O"],"tokens":["si","el","da\u00f1o","contin\u00faa",",","los","ri\u00f1ones","pueden","fallar","."]}
{"ner_tags":["O","B-Concept","O","O","B-Action","O","B-Concept","B-Concept","O"],"tokens":["la","hemofilia","es","un","trastorno","de","coagulaci\u00f3n","hereditario","."]}
{"ner_tags":["B-Concept","O","O","B-Concept","I-Concept","O","B-Action","O","O","B-Concept","O","B-Action","O","O","B-Concept","O","B-Action","O","B-Concept","O","O","B-Concept","O"],"tokens":["normalmente",",","el","\u00e1cido","\u00farico","se","disuelve","en","la","sangre",",","pasa","por","los","ri\u00f1ones","y","sale","del","cuerpo","en","la","orina","."]}
{"ner_tags":["O","B-Concept","B-Concept","O","B-Concept","B-Concept","O","O","B-Action","O","B-Action","O","B-Concept","O","O","B-Action","O"],"tokens":["las","dentaduras","postizas","son","dientes","falsos","que","se","hacen","para","reemplazar","los","dientes","que","se","pierden","."]}
{"ner_tags":["O","B-Concept","B-Action","O","B-Predicate","O","B-Predicate","O","O","B-Concept","O"],"tokens":["la","computadora","convierte","los","ecos","en","im\u00e1genes","de","su","coraz\u00f3n","."]}
{"ner_tags":["O","B-Concept","B-Predicate","B-Concept","O","O","O","O","O","B-Action","B-Action","O","B-Concept","B-Concept","O","O","O","B-Concept","O"],"tokens":["las","personas","con","vih\/sida","tambi\u00e9n","tienen","m\u00e1s","posibilidades","de","sufrir","complicaciones","de","enfermedades","comunes",",","como","la","gripe","."]}
{"ner_tags":["O","B-Concept","B-Action","O","B-Action","O","O","B-Concept","O","B-Action","O","B-Action","O","B-Concept","O"],"tokens":["una","adecuada","inspecci\u00f3n","y","mantenimiento","de","las","m\u00e1quinas","puede","ayudar","a","prevenir","los","accidentes","."]}
{"ner_tags":["O","B-Concept","O","O","B-Concept","I-Concept","O","B-Concept","B-Concept","O","B-Concept","O","B-Concept","O","B-Concept","I-Concept","I-Concept","O"],"tokens":["la","basura","puede","incluir","desperdicios","t\u00f3xicos","como","pilas","viejas",",","insecticidas","en","aerosol","y","diluyente","de","pintura","."]}
{"ner_tags":["O","B-Concept","I-Concept","O","O","O","B-Predicate","B-Concept","O","B-Concept","O"],"tokens":["la","columna","vertebral","est\u00e1","formada","por","26","huesos","llamados","v\u00e9rtebras","."]}
{"ner_tags":["O","B-Concept","O","O","O","B-Action","O","B-Concept","O"],"tokens":["la","asesor\u00eda","puede","ayudarla","a","sobrellevar","el","dolor","."]}
{"ner_tags":["O","B-Concept","B-Concept","O","B-Action","O","B-Action","O","O","B-Concept","O"],"tokens":["los","s\u00edntomas","prematuros","incluyen","dolor","y","rigidez","en","la","espalda","."]}
{"ner_tags":["O","B-Action","O","O","B-Action","B-Concept","O","O","B-Concept","O","B-Action","O","B-Concept","O"],"tokens":["el","estiramiento","o","el","masaje","suave","sobre","el","m\u00fasculo","pueden","aliviar","el","dolor","."]}